astutus/__init__.py
astutus/version.py
astutus/db/__init__.py
astutus/db/logger_db.py
astutus/db/raspi_db.py
astutus/db/sqlite_db.py
astutus/log/__init__.py
astutus/log/log_impl.py
astutus/raspi/__init__.py
astutus/raspi/find.py
astutus/raspi/raspi_impl.py
astutus/sphinx/__init__.py
astutus/sphinx/dyn_pages.py
astutus/sphinx/post_process.py
astutus/usb/__init__.py
astutus/usb/device_aliases.py
astutus/usb/device_classifier.py
astutus/usb/device_configurations.json
astutus/usb/device_configurations.py
astutus/usb/lcus_1_usb_relay.py
astutus/usb/node.py
astutus/usb/node_data.py
astutus/usb/tree.py
astutus/usb/usb_impl.py
astutus/util/__init__.py
astutus/util/pci.py
astutus/util/term_color.py
astutus/util/util_impl.py
astutus/web/__init__.py
astutus/web/app_pages.py
astutus/web/doc_pages.py
astutus/web/flask_app.py
astutus/web/log_pages.py
astutus/web/raspi_pages.py
astutus/web/usb_pages.py
astutus/web/html/genindex.html
astutus/web/html/index.html
astutus/web/html/objects.inv
astutus/web/html/py-modindex.html
astutus/web/html/search.html
astutus/web/html/searchindex.js
astutus/web/html/_sources/index.rst.txt
astutus/web/html/_sources/app/index.rst.txt
astutus/web/html/_sources/app/log/index.rst.txt
astutus/web/html/_sources/app/raspi/index.rst.txt
astutus/web/html/_sources/app/raspi/idx/ifconfig.rst.txt
astutus/web/html/_sources/app/raspi/idx/index.rst.txt
astutus/web/html/_sources/app/usb/alias.rst.txt
astutus/web/html/_sources/app/usb/alias_item.rst.txt
astutus/web/html/_sources/app/usb/device_id.rst.txt
astutus/web/html/_sources/app/usb/device_id_item.rst.txt
astutus/web/html/_sources/app/usb/device_item.rst.txt
astutus/web/html/_sources/app/usb/device_tree.rst.txt
astutus/web/html/_sources/app/usb/index.rst.txt
astutus/web/html/_sources/doc/changes.rst.txt
astutus/web/html/_sources/doc/index.rst.txt
astutus/web/html/_sources/doc/roadmap_to_documentation.rst.txt
astutus/web/html/_sources/doc/welcome.rst.txt
astutus/web/html/_sources/doc/maintanence/design.rst.txt
astutus-0.1.9.202102011217.dist-info/METADATA
astutus-0.1.9.202102011217.dist-info/WHEEL
astutus-0.1.9.202102011217.dist-info/entry_points.txt
astutus-0.1.9.202102011217.dist-info/top_level.txt
astutus-0.1.9.202102011217.dist-info/RECORD
