Metadata-Version: 2.1
Name: astutus
Version: 0.1.9.202102011217
Summary: Use the Sphinx RTD Theme to create a beautiful Flask application.
Home-page: https://github.com/rich-dobbs-13440/astutus/
Author: Rich Dobbs
Author-email: rich.dobbs.13440@gmail.com
License: 'BSD 3-Clause License'
Platform: UNKNOWN
Classifier: Programming Language :: Python :: 3
Classifier: Framework :: Flask
Classifier: Framework :: Sphinx :: Extension
Classifier: Operating System :: POSIX :: Linux
Requires-Dist: Flask
Requires-Dist: sphinx
Requires-Dist: sphinx-rtd-theme
Requires-Dist: flask-sqlalchemy
Requires-Dist: serial
Requires-Dist: wheel
Requires-Dist: treelib
Requires-Dist: webcolors
Requires-Dist: pymemcache
